weighted_cardinality_estimation/__init__.py
weighted_cardinality_estimation/__init__.pyi
weighted_cardinality_estimation/_bindings.cpp
weighted_cardinality_estimation/_core.cpython-314-x86_64-linux-musl.so
weighted_cardinality_estimation/base_log_exp_sketch.cpp
weighted_cardinality_estimation/base_log_exp_sketch.hpp
weighted_cardinality_estimation/base_q_sketch.cpp
weighted_cardinality_estimation/base_q_sketch.hpp
weighted_cardinality_estimation/base_shifted_log_exp_sketch.cpp
weighted_cardinality_estimation/base_shifted_log_exp_sketch.hpp
weighted_cardinality_estimation/exp_sketch.cpp
weighted_cardinality_estimation/exp_sketch.hpp
weighted_cardinality_estimation/fast_exp_sketch.cpp
weighted_cardinality_estimation/fast_exp_sketch.hpp
weighted_cardinality_estimation/fast_log_exp_sketch.cpp
weighted_cardinality_estimation/fast_log_exp_sketch.hpp
weighted_cardinality_estimation/fast_q_sketch.cpp
weighted_cardinality_estimation/fast_q_sketch.hpp
weighted_cardinality_estimation/fast_shifted_log_exp_sketch.cpp
weighted_cardinality_estimation/fast_shifted_log_exp_sketch.hpp
weighted_cardinality_estimation/fastgm_exp_sketch.cpp
weighted_cardinality_estimation/fastgm_exp_sketch.hpp
weighted_cardinality_estimation/fisher_yates.cpp
weighted_cardinality_estimation/fisher_yates.hpp
weighted_cardinality_estimation/hash_util.hpp
weighted_cardinality_estimation/py.typed
weighted_cardinality_estimation/q_sketch.cpp
weighted_cardinality_estimation/q_sketch.hpp
weighted_cardinality_estimation/q_sketch_dyn.cpp
weighted_cardinality_estimation/q_sketch_dyn.hpp
weighted_cardinality_estimation/seeds.cpp
weighted_cardinality_estimation/seeds.hpp
weighted_cardinality_estimation/shifted_log_exp_sketch_structure.cpp
weighted_cardinality_estimation/shifted_log_exp_sketch_structure.hpp
weighted_cardinality_estimation/sketch.hpp
weighted_cardinality_estimation/utils.cpp
weighted_cardinality_estimation/utils.hpp
weighted_cardinality_estimation-0.0.2.dist-info/METADATA
weighted_cardinality_estimation-0.0.2.dist-info/WHEEL
weighted_cardinality_estimation-0.0.2.dist-info/RECORD
